dbus_signature_pyparsing/__init__.py
dbus_signature_pyparsing/_parsing.py
dbus_signature_pyparsing/_version.py
dbus_signature_pyparsing-0.4.1.dist-info/LICENSE
dbus_signature_pyparsing-0.4.1.dist-info/METADATA
dbus_signature_pyparsing-0.4.1.dist-info/WHEEL
dbus_signature_pyparsing-0.4.1.dist-info/top_level.txt
dbus_signature_pyparsing-0.4.1.dist-info/RECORD
