Metadata-Version: 2.1
Name: dbus-signature-pyparsing
Version: 0.4.1
Summary: "dbus signature parser"
Home-page: https://github.com/stratis-storage/dbus-signature-pyparsing
Author: Anne Mulhern
Author-email: amulhern@redhat.com
License: Apache-2.0
Platform: Linux
Classifier: Development Status :: 4 - Beta
Classifier: Intended Audience :: Developers
Classifier: License :: OSI Approved :: Apache Software License
Classifier: Operating System :: POSIX :: Linux
Classifier: Programming Language :: Python
Classifier: Programming Language :: Python :: 3
Classifier: Programming Language :: Python :: Implementation :: CPython
Classifier: Programming Language :: Python :: Implementation :: PyPy
Classifier: Topic :: Software Development :: Libraries
Classifier: Topic :: Software Development :: Libraries :: Python Modules
License-File: LICENSE
Requires-Dist: pyparsing
